datacustomcode/__init__.py
datacustomcode/auth.py
datacustomcode/cli.py
datacustomcode/client.py
datacustomcode/cmd.py
datacustomcode/config.py
datacustomcode/config.yaml
datacustomcode/credentials.py
datacustomcode/deploy.py
datacustomcode/file/__init__.py
datacustomcode/file/base.py
datacustomcode/file/path/__init__.py
datacustomcode/file/path/default.py
datacustomcode/io/__init__.py
datacustomcode/io/base.py
datacustomcode/io/reader/__init__.py
datacustomcode/io/reader/base.py
datacustomcode/io/reader/query_api.py
datacustomcode/io/writer/__init__.py
datacustomcode/io/writer/base.py
datacustomcode/io/writer/csv.py
datacustomcode/io/writer/print.py
datacustomcode/mixin.py
datacustomcode/py.typed
datacustomcode/run.py
datacustomcode/scan.py
datacustomcode/spark/__init__.py
datacustomcode/spark/base.py
datacustomcode/spark/default.py
datacustomcode/template.py
datacustomcode/templates/function/.devcontainer/devcontainer.json
datacustomcode/templates/function/Dockerfile
datacustomcode/templates/function/Dockerfile.dependencies
datacustomcode/templates/function/README.md
datacustomcode/templates/function/account.ipynb
datacustomcode/templates/function/build_native_dependencies.sh
datacustomcode/templates/function/examples/employee_hierarchy/employee_data.csv
datacustomcode/templates/function/examples/employee_hierarchy/entrypoint.py
datacustomcode/templates/function/jupyterlab.sh
datacustomcode/templates/function/payload/config.json
datacustomcode/templates/function/payload/entrypoint.py
datacustomcode/templates/function/requirements-dev.txt
datacustomcode/templates/function/requirements.txt
datacustomcode/templates/script/.devcontainer/devcontainer.json
datacustomcode/templates/script/Dockerfile
datacustomcode/templates/script/Dockerfile.dependencies
datacustomcode/templates/script/README.md
datacustomcode/templates/script/account.ipynb
datacustomcode/templates/script/build_native_dependencies.sh
salesforce_data_customcode-0.1.19.dist-info/METADATA
salesforce_data_customcode-0.1.19.dist-info/WHEEL
salesforce_data_customcode-0.1.19.dist-info/entry_points.txt
salesforce_data_customcode-0.1.19.dist-info/licenses/LICENSE.txt
salesforce_data_customcode-0.1.19.dist-info/RECORD
