Metadata-Version: 2.4
Name: salesforce-data-customcode
Version: 0.1.19
Summary: Data Cloud Custom Code SDK
License-Expression: Apache-2.0
License-File: LICENSE.txt
Requires-Python: >=3.10,<3.12
Classifier: Development Status :: 4 - Beta
Classifier: Operating System :: Unix
Classifier: Programming Language :: Python
Classifier: Programming Language :: Python :: 3
Classifier: Programming Language :: Python :: 3.10
Classifier: Programming Language :: Python :: 3.11
Requires-Dist: click (>=8.1.8,<9.0.0)
Requires-Dist: loguru (>=0.7.3,<0.8.0)
Requires-Dist: numpy
Requires-Dist: pandas
Requires-Dist: pydantic (>=1.8.2,<3.0.0)
Requires-Dist: pyspark (==3.5.1)
Requires-Dist: pyyaml (>=6.0,<7.0)
Requires-Dist: salesforce-cdp-connector
Requires-Dist: setuptools_scm (>=7.1.0,<8.0.0)
